README.md
setup.cfg
setup.py
./ktrade/__init__.py
./ktrade/client.py
./ktrade/exceptions.py
./ktrade/provider.py
./ktrade/providerdict.py
./ktrade/service.py
./ktrade/tunnel.py
./ktrade/version.py
./ktrade/protocol/__init__.py
./ktrade/protocol/run_codegen.py
./ktrade/protocol/stock_pb2.py
./ktrade/protocol/tunnel_pb2.py
./ktrade/stock/__init__.py
./ktrade/stock/async_client.py
./ktrade/stock/async_stockhandler.py
./ktrade/stock/async_stockprovider.py
./ktrade/stock/async_stocksubscriber.py
ktrade.egg-info/PKG-INFO
ktrade.egg-info/SOURCES.txt
ktrade.egg-info/dependency_links.txt
ktrade.egg-info/not-zip-safe
ktrade.egg-info/top_level.txt